telebot_mem/__init__.py
telebot_mem/db.py
telebot_mem/mongo_db.py
telebot_mem-0.1.2.dist-info/METADATA
telebot_mem-0.1.2.dist-info/WHEEL
telebot_mem-0.1.2.dist-info/top_level.txt
telebot_mem-0.1.2.dist-info/RECORD
