Metadata-Version: 2.1
Name: telebot_mem
Version: 0.1.2
Summary: Telebot with memory extension. It supports add a database backend to save chat histories.
Author-email: Wei Li <weilinear@gmail.com>
Project-URL: Homepage, https://github.com/weilinear/telebot_mem
Project-URL: Issues, https://github.com/weilinear/telebot_mem/issues
Classifier: Programming Language :: Python :: 3
Classifier: License :: OSI Approved :: Apache Software License
Classifier: Operating System :: OS Independent
Requires-Python: >=3.8
Requires-Dist: pymongo
Requires-Dist: pyTelegramBotAPI
